TODO.txt
__init__.py
domstripper.py
setup.cfg
setup.py
test_domstripper.py
domstripper.egg-info/PKG-INFO
domstripper.egg-info/SOURCES.txt
domstripper.egg-info/dependency_links.txt
domstripper.egg-info/entry_points.txt
domstripper.egg-info/requires.txt
domstripper.egg-info/top_level.txt
domstripper.egg-info/zip-safe