Metadata-Version: 1.0
Name: domstripper
Version: 0.4dev-r16670
Summary: lxml.html based DOM manipulator
Home-page: http://www.peterbe.com/plog/domstripper
Author: Peter Bengtsson
Author-email: peter@fry-it.com
License: GPL
Keywords: html xml dom
Platform: UNKNOWN
